README.rst
setup.cfg
setup.py
RIBBIT/__init__.py
RIBBIT/client.py
RIBBIT/decoder.py
RIBBIT/definition.py
RIBBIT/encoder.py
RIBBIT/scripts/__init__.py
RIBBIT/scripts/cli.py
python_RIBBIT.egg-info/PKG-INFO
python_RIBBIT.egg-info/SOURCES.txt
python_RIBBIT.egg-info/dependency_links.txt
python_RIBBIT.egg-info/entry_points.txt
python_RIBBIT.egg-info/not-zip-safe
python_RIBBIT.egg-info/requires.txt
python_RIBBIT.egg-info/top_level.txt