Metadata-Version: 1.0
Name: python-RIBBIT
Version: 1.0.2.dev0
Summary: frog.tips RIBBIT client
Home-page: https://github.com/gabrielg/python-RIBBIT
Author: Gabriel Gironda
Author-email: gabriel@gironda.org
License: MIT
Keywords: FROG RIBBIT CROAK
Platform: UNKNOWN
